vertopy/__init__.py
vertopy/fungsi_berat.py
vertopy/fungsi_kecepatan.py
vertopy/fungsi_panjang.py
vertopy/fungsi_suhu.py
vertopy/fungsi_waktu.py
vertopy-0.3.dist-info/LICENSE
vertopy-0.3.dist-info/METADATA
vertopy-0.3.dist-info/WHEEL
vertopy-0.3.dist-info/top_level.txt
vertopy-0.3.dist-info/RECORD
