Metadata-Version: 2.1
Name: vertopy
Version: 0.3
Summary: Library untuk konversi unit panjang, berat, suhu, dan waktu
Author: Twinkel-Twinkel
Author-email: bryawanyud@gmail.com
Classifier: Programming Language :: Python :: 3
Classifier: License :: OSI Approved :: MIT License
Classifier: Operating System :: OS Independent
Requires-Python: >=3.6
License-File: LICENSE
